Metadata-Version: 2.1
Name: xlfunctions
Version: 0.0.3b0
Summary: xlfunctions implements Python equivalents of MS Excel formulas.
Home-page: https://github.com/bradbase/xlfunctions
Author: Bradley van Ree
Author-email: brads@bradbase.net
License: UNKNOWN
Platform: UNKNOWN
Classifier: Programming Language :: Python :: 3
Classifier: License :: OSI Approved :: GNU General Public License v3 (GPLv3)
Classifier: Operating System :: OS Independent
Requires-Python: >=3.7.6
Requires-Dist: numpy (>=1.18.1)
Requires-Dist: pandas (>=1.0.1)
Requires-Dist: numpy-financial (>=1.0.0)
